{
  "animateLoading": true,
  "borderRadius": "{{appsmith.theme.borderRadius.appBorderRadius}}",
  "bottomRow": 4,
  "dynamicBindingPathList": [
    {
      "key": "truncateButtonColor"
    },
    {
      "key": "fontFamily"
    },
    {
      "key": "borderRadius"
    },
    {
      "key": "text"
    }
  ],
  "dynamicHeight": "AUTO_HEIGHT",
  "dynamicTriggerPathList": [],
  "fontFamily": "{{appsmith.theme.fontFamily.appFont}}",
  "fontSize": "1rem",
  "fontStyle": "BOLD",
  "isLoading": false,
  "isVisible": true,
  "key": "uxww65lpto",
  "leftColumn": 3,
  "maxDynamicHeight": 9000,
  "minDynamicHeight": 4,
  "minWidth": 450,
  "mobileBottomRow": 4,
  "mobileLeftColumn": 0,
  "mobileRightColumn": 16,
  "mobileTopRow": 0,
  "needsErrorInfo": false,
  "originalBottomRow": 4,
  "originalTopRow": 0,
  "overflow": "NONE",
  "parentColumnSpace": 6.53125,
  "parentId": "7t2a0zelrv",
  "parentRowSpace": 10,
  "renderMode": "CANVAS",
  "responsiveBehavior": "fill",
  "rightColumn": 34,
  "shouldTruncate": false,
  "text": "{{appsmith.store.userName}} {{appsmith.store.lastName}}",
  "textAlign": "LEFT",
  "textColor": "white",
  "topRow": 0,
  "truncateButtonColor": "{{appsmith.theme.colors.primaryColor}}",
  "type": "TEXT_WIDGET",
  "version": 1,
  "widgetId": "ly1jluk6qe",
  "widgetName": "Text3"
}